{
  "version": 1,
  "generated_at": "2026-05-29T06:15:28.432959-04:00",
  "timezone": "America/Toronto",
  "today": {
    "placed_orders": 1,
    "order_value_cad": 67.5,
    "aov_cad": 67.5,
    "customer_mix": {
      "brand_new": 1,
      "second_order": 0,
      "regular": 0,
      "returning_regular_total": 0
    },
    "business_date": "2026-05-29",
    "as_of_et": "2026-05-29T06:15:22.963478-04:00",
    "target_placed_orders": 20,
    "pace_to_target_pct": 5.0,
    "same_time_7d_avg_orders": 0.7,
    "same_time_delta_orders": 0.3,
    "same_time_7d_avg_order_value_cad": 37.5,
    "same_time_7d_avg_new_customers": 0.3,
    "deliveries": {
      "count": 0,
      "revenue_cad": 0.0,
      "aov_cad": 0.0
    }
  },
  "customer_type_labels": {
    "brand_new": "New Customers",
    "second_order": "Second-Order Customers",
    "regular": "Habitual Customers",
    "returning_regular_total": "Second-Order + Habitual Customers"
  },
  "same_time_7d_samples": [
    {
      "date": "2026-05-28",
      "placed_orders": 0,
      "order_value_cad": 0,
      "new_customers": 0
    },
    {
      "date": "2026-05-27",
      "placed_orders": 0,
      "order_value_cad": 0,
      "new_customers": 0
    },
    {
      "date": "2026-05-26",
      "placed_orders": 2,
      "order_value_cad": 88.5,
      "new_customers": 1
    },
    {
      "date": "2026-05-25",
      "placed_orders": 1,
      "order_value_cad": 50.5,
      "new_customers": 0
    },
    {
      "date": "2026-05-24",
      "placed_orders": 0,
      "order_value_cad": 0,
      "new_customers": 0
    },
    {
      "date": "2026-05-23",
      "placed_orders": 2,
      "order_value_cad": 123.5,
      "new_customers": 1
    },
    {
      "date": "2026-05-22",
      "placed_orders": 0,
      "order_value_cad": 0,
      "new_customers": 0
    }
  ],
  "acquisition": {
    "new_customer_orders": 1,
    "sources": [
      {
        "bucket": "Organic Search",
        "orders": 1,
        "confidence": "medium"
      }
    ],
    "classified_orders": [
      {
        "order_id": 5843,
        "bucket": "Organic Search",
        "confidence": "medium",
        "reason": "GA4 matched Google non-paid signal.",
        "match_quality": "ga4_source_signal",
        "campaign": null,
        "referral_code": null,
        "referral_owner_name": null
      }
    ],
    "unknown_orders": 0,
    "ga4_status": {
      "status": "ok",
      "primary": "ga4_data_api",
      "ga4_data_api": {
        "status": "ok",
        "source": "ga4_data_api",
        "rows": 0,
        "row_count": 0,
        "date_start": "2026-05-29",
        "date_end": "2026-05-29",
        "auth": "service_account",
        "credentials": "/home/yoygurt/.config/ga4-mcp/credentials.json"
      },
      "bigquery": {
        "status": "ok",
        "rows": 1,
        "method": "rest"
      },
      "rows": 1
    },
    "appsflyer": {
      "status": "ok",
      "date": "2026-05-29",
      "timezone": "America/Toronto",
      "fetched_at": "2026-05-29T06:15:22.963478-04:00",
      "cache_status": "miss",
      "apps": [
        {
          "status": "ok",
          "app_id": "id6738962991",
          "rows": 0,
          "platform": "ios"
        },
        {
          "status": "ok",
          "app_id": "com.tumbil",
          "rows": 0,
          "platform": "android"
        }
      ],
      "totals": {
        "purchase_events": 0,
        "unique_users": 0,
        "sales_cad": 0.0
      },
      "google_ads_purchase_events": 0,
      "media_sources": [],
      "note": "AppsFlyer aggregate app purchase events by media source. These are not joined to DB orders or customers."
    },
    "caveat": "Order counts and customer status come from DB. Source labels are GA4 attribution-only, with GA4 Data API purchase/tumbil_id matches preferred over BigQuery raw-event fallback. AppsFlyer is included as aggregate app purchase attribution and is not joined to individual customers. Referral promo codes are tracked separately."
  },
  "referrals": {
    "today": {
      "orders": 0,
      "customers": 0,
      "order_value_cad": 0.0
    },
    "seven_day": {
      "orders": 1,
      "customers": 1,
      "order_value_cad": 18.0
    },
    "thirty_day": {
      "orders": 3,
      "customers": 3,
      "order_value_cad": 124.01
    },
    "top_codes_30d": [
      {
        "code": "MIRANR",
        "owner_id": 2096,
        "owner_name": "Miranda-sue Ranger",
        "orders": 3,
        "order_value_cad": 124.01
      }
    ]
  },
  "deliveries_monthly": {
    "current_month": "2026-05",
    "mtd_total_deliveries": 350,
    "mtd_days_elapsed": 29,
    "mtd_avg_per_day": 12.07,
    "monthly_history": [
      {
        "year_month": "2025-05",
        "deliveries": 20,
        "days": 31,
        "avg_per_day": 0.65,
        "is_current_month": false
      },
      {
        "year_month": "2025-06",
        "deliveries": 54,
        "days": 30,
        "avg_per_day": 1.8,
        "is_current_month": false
      },
      {
        "year_month": "2025-07",
        "deliveries": 92,
        "days": 31,
        "avg_per_day": 2.97,
        "is_current_month": false
      },
      {
        "year_month": "2025-08",
        "deliveries": 126,
        "days": 31,
        "avg_per_day": 4.06,
        "is_current_month": false
      },
      {
        "year_month": "2025-09",
        "deliveries": 146,
        "days": 30,
        "avg_per_day": 4.87,
        "is_current_month": false
      },
      {
        "year_month": "2025-10",
        "deliveries": 181,
        "days": 31,
        "avg_per_day": 5.84,
        "is_current_month": false
      },
      {
        "year_month": "2025-11",
        "deliveries": 210,
        "days": 30,
        "avg_per_day": 7.0,
        "is_current_month": false
      },
      {
        "year_month": "2025-12",
        "deliveries": 252,
        "days": 31,
        "avg_per_day": 8.13,
        "is_current_month": false
      },
      {
        "year_month": "2026-01",
        "deliveries": 293,
        "days": 31,
        "avg_per_day": 9.45,
        "is_current_month": false
      },
      {
        "year_month": "2026-02",
        "deliveries": 327,
        "days": 28,
        "avg_per_day": 11.68,
        "is_current_month": false
      },
      {
        "year_month": "2026-03",
        "deliveries": 402,
        "days": 31,
        "avg_per_day": 12.97,
        "is_current_month": false
      },
      {
        "year_month": "2026-04",
        "deliveries": 362,
        "days": 30,
        "avg_per_day": 12.07,
        "is_current_month": false
      },
      {
        "year_month": "2026-05",
        "deliveries": 350,
        "days": 29,
        "avg_per_day": 12.07,
        "is_current_month": true
      }
    ]
  },
  "lifetime_value": {
    "customers": 367,
    "total_orders": 1481,
    "total_revenue_cad": 81394.74,
    "ltv_cad": 221.78,
    "orders_per_customer": 4.04,
    "contribution_per_customer_cad": 49.9,
    "contribution_margin": 0.225,
    "cohort_days": 180,
    "cohort_breakdown": [
      {
        "months_since_first_order": 0,
        "customers": 72,
        "total_orders": 85,
        "orders_per_customer": 1.18,
        "revenue_per_customer_cad": 77.25,
        "ltv_per_customer_cad": 17.38
      },
      {
        "months_since_first_order": 1,
        "customers": 84,
        "total_orders": 167,
        "orders_per_customer": 1.99,
        "revenue_per_customer_cad": 123.32,
        "ltv_per_customer_cad": 27.75
      },
      {
        "months_since_first_order": 2,
        "customers": 98,
        "total_orders": 228,
        "orders_per_customer": 2.33,
        "revenue_per_customer_cad": 127.29,
        "ltv_per_customer_cad": 28.64
      },
      {
        "months_since_first_order": 3,
        "customers": 102,
        "total_orders": 299,
        "orders_per_customer": 2.93,
        "revenue_per_customer_cad": 157.5,
        "ltv_per_customer_cad": 35.44
      },
      {
        "months_since_first_order": 4,
        "customers": 102,
        "total_orders": 307,
        "orders_per_customer": 3.01,
        "revenue_per_customer_cad": 158.13,
        "ltv_per_customer_cad": 35.58
      },
      {
        "months_since_first_order": 5,
        "customers": 89,
        "total_orders": 255,
        "orders_per_customer": 2.87,
        "revenue_per_customer_cad": 153.71,
        "ltv_per_customer_cad": 34.58
      },
      {
        "months_since_first_order": 6,
        "customers": 74,
        "total_orders": 289,
        "orders_per_customer": 3.91,
        "revenue_per_customer_cad": 212.89,
        "ltv_per_customer_cad": 47.9
      },
      {
        "months_since_first_order": 7,
        "customers": 56,
        "total_orders": 207,
        "orders_per_customer": 3.7,
        "revenue_per_customer_cad": 193.49,
        "ltv_per_customer_cad": 43.54
      },
      {
        "months_since_first_order": 8,
        "customers": 68,
        "total_orders": 337,
        "orders_per_customer": 4.96,
        "revenue_per_customer_cad": 277.7,
        "ltv_per_customer_cad": 62.48
      },
      {
        "months_since_first_order": 9,
        "customers": 71,
        "total_orders": 196,
        "orders_per_customer": 2.76,
        "revenue_per_customer_cad": 184.99,
        "ltv_per_customer_cad": 41.62
      },
      {
        "months_since_first_order": 10,
        "customers": 42,
        "total_orders": 189,
        "orders_per_customer": 4.5,
        "revenue_per_customer_cad": 234.6,
        "ltv_per_customer_cad": 52.79
      },
      {
        "months_since_first_order": 11,
        "customers": 36,
        "total_orders": 187,
        "orders_per_customer": 5.19,
        "revenue_per_customer_cad": 265.85,
        "ltv_per_customer_cad": 59.82
      },
      {
        "months_since_first_order": 12,
        "customers": 16,
        "total_orders": 66,
        "orders_per_customer": 4.12,
        "revenue_per_customer_cad": 183.14,
        "ltv_per_customer_cad": 41.21
      },
      {
        "months_since_first_order": 13,
        "customers": 3,
        "total_orders": 5,
        "orders_per_customer": 1.67,
        "revenue_per_customer_cad": 76.67,
        "ltv_per_customer_cad": 17.25
      },
      {
        "months_since_first_order": 14,
        "customers": 1,
        "total_orders": 5,
        "orders_per_customer": 5.0,
        "revenue_per_customer_cad": 204.0,
        "ltv_per_customer_cad": 45.9
      }
    ],
    "sensitivity": [
      {
        "cohort_days": 0,
        "customers": 914,
        "total_orders": 2822,
        "orders_per_customer": 3.09,
        "revenue_per_customer_cad": 170.31,
        "ltv_per_customer_cad": 38.32
      },
      {
        "cohort_days": 30,
        "customers": 842,
        "total_orders": 2737,
        "orders_per_customer": 3.25,
        "revenue_per_customer_cad": 178.27,
        "ltv_per_customer_cad": 40.11
      },
      {
        "cohort_days": 60,
        "customers": 758,
        "total_orders": 2570,
        "orders_per_customer": 3.39,
        "revenue_per_customer_cad": 184.36,
        "ltv_per_customer_cad": 41.48
      },
      {
        "cohort_days": 90,
        "customers": 660,
        "total_orders": 2342,
        "orders_per_customer": 3.55,
        "revenue_per_customer_cad": 192.83,
        "ltv_per_customer_cad": 43.39
      },
      {
        "cohort_days": 120,
        "customers": 558,
        "total_orders": 2043,
        "orders_per_customer": 3.66,
        "revenue_per_customer_cad": 199.29,
        "ltv_per_customer_cad": 44.84
      },
      {
        "cohort_days": 180,
        "customers": 367,
        "total_orders": 1481,
        "orders_per_customer": 4.04,
        "revenue_per_customer_cad": 221.78,
        "ltv_per_customer_cad": 49.9
      },
      {
        "cohort_days": 270,
        "customers": 169,
        "total_orders": 648,
        "orders_per_customer": 3.83,
        "revenue_per_customer_cad": 212.56,
        "ltv_per_customer_cad": 47.83
      },
      {
        "cohort_days": 365,
        "customers": 17,
        "total_orders": 69,
        "orders_per_customer": 4.06,
        "revenue_per_customer_cad": 177.41,
        "ltv_per_customer_cad": 39.92
      }
    ]
  },
  "data_health": {
    "db": {
      "status": "ok",
      "as_of_et": "2026-05-29T06:15:22.963478-04:00"
    },
    "ga4_attribution": {
      "status": "ok",
      "primary": "ga4_data_api",
      "ga4_data_api": {
        "status": "ok",
        "source": "ga4_data_api",
        "rows": 0,
        "row_count": 0,
        "date_start": "2026-05-29",
        "date_end": "2026-05-29",
        "auth": "service_account",
        "credentials": "/home/yoygurt/.config/ga4-mcp/credentials.json"
      },
      "bigquery": {
        "status": "ok",
        "rows": 1,
        "method": "rest"
      },
      "rows": 1
    },
    "ga4_bigquery": {
      "status": "ok",
      "rows": 1,
      "method": "rest"
    },
    "appsflyer": {
      "status": "ok",
      "date": "2026-05-29",
      "apps": [
        {
          "status": "ok",
          "app_id": "id6738962991",
          "rows": 0,
          "platform": "ios"
        },
        {
          "status": "ok",
          "app_id": "com.tumbil",
          "rows": 0,
          "platform": "android"
        }
      ]
    },
    "priorities": {
      "status": "ok",
      "updated_at": "2026-05-13T11:35:13.462694-04:00",
      "item_count": 122
    }
  }
}